[
  {
    "lang_code": "am", 
    "contributors": [
      {
        "full": "Binyam Ephrem", 
        "last": "Ephrem", 
        "first": "Binyam"
      }
    ], 
    "lang_name": "Amharic"
  }, 
  {
    "lang_code": "grc", 
    "contributors": [
      {
        "full": "Giuseppe G. A. Celano", 
        "last": "Celano", 
        "first": "Giuseppe G. A."
      }, 
      {
        "full": "Daniel Zeman", 
        "last": "Zeman", 
        "first": "Daniel"
      }
    ], 
    "lang_name": "Ancient_Greek"
  }, 
  {
    "lang_code": "grc_proiel", 
    "contributors": [
      {
        "full": "Dag Haug", 
        "last": "Haug", 
        "first": "Dag"
      }
    ], 
    "lang_name": "Ancient_Greek-PROIEL"
  }, 
  {
    "lang_code": "ar", 
    "contributors": [
      {
        "full": "Daniel Zeman", 
        "last": "Zeman", 
        "first": "Daniel"
      }, 
      {
        "full": "Zden\u011bk \u017dabokrtsk\u00fd", 
        "last": "\u017dabokrtsk\u00fd", 
        "first": "Zden\u011bk"
      }, 
      {
        "full": "Shadi Saleh", 
        "last": "Saleh", 
        "first": "Shadi"
      }
    ], 
    "lang_name": "Arabic"
  }, 
  {
    "lang_code": "eu", 
    "contributors": [
      {
        "full": "Maria Jesus Aranzabe", 
        "last": "Aranzabe", 
        "first": "Maria Jesus"
      }, 
      {
        "full": "Aitziber Atutxa", 
        "last": "Atutxa", 
        "first": "Aitziber"
      }, 
      {
        "full": "Kepa Bengoetxea", 
        "last": "Bengoetxea", 
        "first": "Kepa"
      }, 
      {
        "full": "Arantza Diaz de Ilarraza", 
        "last": "Diaz de Ilarraza", 
        "first": "Arantza"
      }, 
      {
        "full": "Iakes Goenaga", 
        "last": "Goenaga", 
        "first": "Iakes"
      }, 
      {
        "full": "Koldo Gojenola", 
        "last": "Gojenola", 
        "first": "Koldo"
      }, 
      {
        "full": "Larraitz Uria", 
        "last": "Uria", 
        "first": "Larraitz"
      }
    ], 
    "lang_name": "Basque"
  }, 
  {
    "lang_code": "bg", 
    "contributors": [
      {
        "full": "Kiril Simov", 
        "last": "Simov", 
        "first": "Kiril"
      }, 
      {
        "full": "Petya Osenova", 
        "last": "Osenova", 
        "first": "Petya"
      }
    ], 
    "lang_name": "Bulgarian"
  }, 
  {
    "lang_code": "bxr", 
    "contributors": [
      {
        "full": "Elena Badmaeva", 
        "last": "Badmaeva", 
        "first": "Elena"
      }, 
      {
        "full": "Francis Tyers", 
        "last": "Tyers", 
        "first": "Francis"
      }
    ], 
    "lang_name": "Buryat"
  }, 
  {
    "lang_code": "ca", 
    "contributors": [
      {
        "full": "H\u00e9ctor Mart\u00ednez Alonso", 
        "last": "Mart\u00ednez Alonso", 
        "first": "H\u00e9ctor"
      }, 
      {
        "full": "Elena Pascual", 
        "last": "Pascual", 
        "first": "Elena"
      }, 
      {
        "full": "Daniel Zeman", 
        "last": "Zeman", 
        "first": "Daniel"
      }
    ], 
    "lang_name": "Catalan"
  }, 
  {
    "lang_code": "zh", 
    "contributors": [
      {
        "full": "Mo Shen", 
        "last": "Shen", 
        "first": "Mo"
      }, 
      {
        "full": "Ryan McDonald", 
        "last": "McDonald", 
        "first": "Ryan"
      }
    ], 
    "lang_name": "Chinese"
  }, 
  {
    "lang_code": "cop", 
    "contributors": [
      {
        "full": "Amir Zeldes", 
        "last": "Zeldes", 
        "first": "Amir"
      }
    ], 
    "lang_name": "Coptic"
  }, 
  {
    "lang_code": "hr", 
    "contributors": [
      {
        "full": "\u017deljko Agi\u0107", 
        "last": "Agi\u0107", 
        "first": "\u017deljko"
      }, 
      {
        "full": "Nikola Ljube\u0161i\u0107", 
        "last": "Ljube\u0161i\u0107", 
        "first": "Nikola"
      }
    ], 
    "lang_name": "Croatian"
  }, 
  {
    "lang_code": "cs", 
    "contributors": [
      {
        "full": "Daniel Zeman", 
        "last": "Zeman", 
        "first": "Daniel"
      }, 
      {
        "full": "Jan Haji\u010d", 
        "last": "Haji\u010d", 
        "first": "Jan"
      }
    ], 
    "lang_name": "Czech"
  }, 
  {
    "lang_code": "cs_cac", 
    "contributors": [
      {
        "full": "Barbora Hladk\u00e1", 
        "last": "Hladk\u00e1", 
        "first": "Barbora"
      }, 
      {
        "full": "Daniel Zeman", 
        "last": "Zeman", 
        "first": "Daniel"
      }
    ], 
    "lang_name": "Czech-CAC"
  }, 
  {
    "lang_code": "cs_cltt", 
    "contributors": [
      {
        "full": "Barbora Hladk\u00e1", 
        "last": "Hladk\u00e1", 
        "first": "Barbora"
      }, 
      {
        "full": "Daniel Zeman", 
        "last": "Zeman", 
        "first": "Daniel"
      }
    ], 
    "lang_name": "Czech-CLTT"
  }, 
  {
    "lang_code": "da", 
    "contributors": [
      {
        "full": "Anders Johannsen", 
        "last": "Johannsen", 
        "first": "Anders"
      }, 
      {
        "full": "H\u00e9ctor Mart\u00ednez Alonso", 
        "last": "Mart\u00ednez Alonso", 
        "first": "H\u00e9ctor"
      }, 
      {
        "full": "Barbara Plank", 
        "last": "Plank", 
        "first": "Barbara"
      }
    ], 
    "lang_name": "Danish"
  }, 
  {
    "lang_code": "nl", 
    "contributors": [
      {
        "full": "Daniel Zeman", 
        "last": "Zeman", 
        "first": "Daniel"
      }, 
      {
        "full": "Zden\u011bk \u017dabokrtsk\u00fd", 
        "last": "\u017dabokrtsk\u00fd", 
        "first": "Zden\u011bk"
      }
    ], 
    "lang_name": "Dutch"
  }, 
  {
    "lang_code": "nl_lassysmall", 
    "contributors": [
      {
        "full": "Gosse Bouma", 
        "last": "Bouma", 
        "first": "Gosse"
      }, 
      {
        "full": "Gertjan van Noord", 
        "last": "van Noord", 
        "first": "Gertjan"
      }
    ], 
    "lang_name": "Dutch-LassySmall"
  }, 
  {
    "lang_code": "en", 
    "contributors": [
      {
        "full": "Natalia Silveira", 
        "last": "Silveira", 
        "first": "Natalia"
      }, 
      {
        "full": "Timothy Dozat", 
        "last": "Dozat", 
        "first": "Timothy"
      }, 
      {
        "full": "Christopher Manning", 
        "last": "Manning", 
        "first": "Christopher"
      }, 
      {
        "full": "Sebastian Schuster", 
        "last": "Schuster", 
        "first": "Sebastian"
      }, 
      {
        "full": "John Bauer", 
        "last": "Bauer", 
        "first": "John"
      }, 
      {
        "full": "Miriam Connor", 
        "last": "Connor", 
        "first": "Miriam"
      }, 
      {
        "full": "Marie-Catherine de Marneffe", 
        "last": "de Marneffe", 
        "first": "Marie-Catherine"
      }, 
      {
        "full": "Sam Bowman", 
        "last": "Bowman", 
        "first": "Sam"
      }, 
      {
        "full": "Hanzhi Zhu", 
        "last": "Zhu", 
        "first": "Hanzhi"
      }, 
      {
        "full": "Daniel Galbraith", 
        "last": "Galbraith", 
        "first": "Daniel"
      }
    ], 
    "lang_name": "English"
  }, 
  {
    "lang_code": "en_esl", 
    "contributors": [
      {
        "full": "Yevgeni Berzak", 
        "last": "Berzak", 
        "first": "Yevgeni"
      }, 
      {
        "full": "Jessica Kenney", 
        "last": "Kenney", 
        "first": "Jessica"
      }, 
      {
        "full": "Carolyn Spadine", 
        "last": "Spadine", 
        "first": "Carolyn"
      }, 
      {
        "full": "Jing Xian Wang", 
        "last": "Wang", 
        "first": "Jing Xian"
      }, 
      {
        "full": "Lucia Lam", 
        "last": "Lam", 
        "first": "Lucia"
      }, 
      {
        "full": "Keiko Sophie Mori", 
        "last": "Mori", 
        "first": "Keiko Sophie"
      }, 
      {
        "full": "Sebastian Garza", 
        "last": "Garza", 
        "first": "Sebastian"
      }, 
      {
        "full": "Boris Katz", 
        "last": "Katz", 
        "first": "Boris"
      }
    ], 
    "lang_name": "English-ESL"
  }, 
  {
    "lang_code": "en_lines", 
    "contributors": [
      {
        "full": "Lars Ahrenberg", 
        "last": "Ahrenberg", 
        "first": "Lars"
      }
    ], 
    "lang_name": "English-LinES"
  }, 
  {
    "lang_code": "et", 
    "contributors": [
      {
        "full": "Kadri Muischnek", 
        "last": "Muischnek", 
        "first": "Kadri"
      }, 
      {
        "full": "Kaili M\u00fc\u00fcrisep", 
        "last": "M\u00fc\u00fcrisep", 
        "first": "Kaili"
      }, 
      {
        "full": "Tiina Puolakainen", 
        "last": "Puolakainen", 
        "first": "Tiina"
      }
    ], 
    "lang_name": "Estonian"
  }, 
  {
    "lang_code": "fi", 
    "contributors": [
      {
        "full": "Filip Ginter", 
        "last": "Ginter", 
        "first": "Filip"
      }, 
      {
        "full": "Jenna Kanerva", 
        "last": "Kanerva", 
        "first": "Jenna"
      }, 
      {
        "full": "Veronika Laippala", 
        "last": "Laippala", 
        "first": "Veronika"
      }, 
      {
        "full": "Anna Missil\u00e4", 
        "last": "Missil\u00e4", 
        "first": "Anna"
      }, 
      {
        "full": "Sampo Pyysalo", 
        "last": "Pyysalo", 
        "first": "Sampo"
      }
    ], 
    "lang_name": "Finnish"
  }, 
  {
    "lang_code": "fi_ftb", 
    "contributors": [
      {
        "full": "Jussi Piitulainen", 
        "last": "Piitulainen", 
        "first": "Jussi"
      }, 
      {
        "full": "Hanna Nurmi", 
        "last": "Nurmi", 
        "first": "Hanna"
      }
    ], 
    "lang_name": "Finnish-FTB"
  }, 
  {
    "lang_code": "fr", 
    "contributors": [
      {
        "full": "Marie-Catherine de Marneffe", 
        "last": "de Marneffe", 
        "first": "Marie-Catherine"
      }, 
      {
        "full": "Bruno Guillaume", 
        "last": "Guillaume", 
        "first": "Bruno"
      }, 
      {
        "full": "Ryan McDonald", 
        "last": "McDonald", 
        "first": "Ryan"
      }, 
      {
        "full": "Alane Suhr", 
        "last": "Suhr", 
        "first": "Alane"
      }, 
      {
        "full": "Joakim Nivre", 
        "last": "Nivre", 
        "first": "Joakim"
      }
    ], 
    "lang_name": "French"
  }, 
  {
    "lang_code": "gl", 
    "contributors": [
      {
        "full": "Xavier G\u00f3mez Guinovart", 
        "last": "G\u00f3mez Guinovart", 
        "first": "Xavier"
      }
    ], 
    "lang_name": "Galician"
  }, 
  {
    "lang_code": "de", 
    "contributors": [
      {
        "full": "Slav Petrov", 
        "last": "Petrov", 
        "first": "Slav"
      }, 
      {
        "full": "Wolfgang Seeker", 
        "last": "Seeker", 
        "first": "Wolfgang"
      }, 
      {
        "full": "Ryan McDonald", 
        "last": "McDonald", 
        "first": "Ryan"
      }, 
      {
        "full": "Joakim Nivre", 
        "last": "Nivre", 
        "first": "Joakim"
      }
    ], 
    "lang_name": "German"
  }, 
  {
    "lang_code": "got", 
    "contributors": [
      {
        "full": "Dag Haug", 
        "last": "Haug", 
        "first": "Dag"
      }
    ], 
    "lang_name": "Gothic"
  }, 
  {
    "lang_code": "el", 
    "contributors": [
      {
        "full": "Prokopis Prokopidis", 
        "last": "Prokopidis", 
        "first": "Prokopis"
      }
    ], 
    "lang_name": "Greek"
  }, 
  {
    "lang_code": "he", 
    "contributors": [
      {
        "full": "Yoav Goldberg", 
        "last": "Goldberg", 
        "first": "Yoav"
      }, 
      {
        "full": "Reut Tsarfaty", 
        "last": "Tsarfaty", 
        "first": "Reut"
      }
    ], 
    "lang_name": "Hebrew"
  }, 
  {
    "lang_code": "hi", 
    "contributors": [
      {
        "full": "Riyaz Ahmad Bhat", 
        "last": "Bhat", 
        "first": "Riyaz Ahmad"
      }, 
      {
        "full": "Daniel Zeman", 
        "last": "Zeman", 
        "first": "Daniel"
      }
    ], 
    "lang_name": "Hindi"
  }, 
  {
    "lang_code": "hu", 
    "contributors": [
      {
        "full": "Rich\u00e1rd Farkas", 
        "last": "Farkas", 
        "first": "Rich\u00e1rd"
      }, 
      {
        "full": "Katalin Simk\u00f3", 
        "last": "Simk\u00f3", 
        "first": "Katalin"
      }, 
      {
        "full": "Zsolt Sz\u00e1nt\u00f3", 
        "last": "Sz\u00e1nt\u00f3", 
        "first": "Zsolt"
      }, 
      {
        "full": "Viktor Varga", 
        "last": "Varga", 
        "first": "Viktor"
      }, 
      {
        "full": "Veronika Vincze", 
        "last": "Vincze", 
        "first": "Veronika"
      }
    ], 
    "lang_name": "Hungarian"
  }, 
  {
    "lang_code": "id", 
    "contributors": [
      {
        "full": "Ryan McDonald", 
        "last": "McDonald", 
        "first": "Ryan"
      }, 
      {
        "full": "Joakim Nivre", 
        "last": "Nivre", 
        "first": "Joakim"
      }
    ], 
    "lang_name": "Indonesian"
  }, 
  {
    "lang_code": "ga", 
    "contributors": [
      {
        "full": "Teresa Lynn", 
        "last": "Lynn", 
        "first": "Teresa"
      }, 
      {
        "full": "Jennifer Foster", 
        "last": "Foster", 
        "first": "Jennifer"
      }
    ], 
    "lang_name": "Irish"
  }, 
  {
    "lang_code": "it", 
    "contributors": [
      {
        "full": "Cristina Bosco", 
        "last": "Bosco", 
        "first": "Cristina"
      }, 
      {
        "full": "Alessandro Lenci", 
        "last": "Lenci", 
        "first": "Alessandro"
      }, 
      {
        "full": "Simonetta Montemagni", 
        "last": "Montemagni", 
        "first": "Simonetta"
      }, 
      {
        "full": "Maria Simi", 
        "last": "Simi", 
        "first": "Maria"
      }
    ], 
    "lang_name": "Italian"
  }, 
  {
    "lang_code": "ja_ktc", 
    "contributors": [
      {
        "full": "Masayuki Asahara", 
        "last": "Asahara", 
        "first": "Masayuki"
      }, 
      {
        "full": "Hiroshi Kanayama", 
        "last": "Kanayama", 
        "first": "Hiroshi"
      }, 
      {
        "full": "Yuji Matsumoto", 
        "last": "Matsumoto", 
        "first": "Yuji"
      }, 
      {
        "full": "Yusuke Miyao", 
        "last": "Miyao", 
        "first": "Yusuke"
      }, 
      {
        "full": "Shunsuke Mori", 
        "last": "Mori", 
        "first": "Shunsuke"
      }, 
      {
        "full": "Takaaki Tanaka", 
        "last": "Tanaka", 
        "first": "Takaaki"
      }, 
      {
        "full": "Sumire Uematsu", 
        "last": "Uematsu", 
        "first": "Sumire"
      }
    ], 
    "lang_name": "Japanese-KTC"
  }, 
  {
    "lang_code": "kk", 
    "contributors": [
      {
        "full": "Aibek Makazhanov", 
        "last": "Makazhanov", 
        "first": "Aibek"
      }, 
      {
        "full": "Jonathan North Washington", 
        "last": "Washington", 
        "first": "Jonathan North"
      }, 
      {
        "full": "Francis Tyers", 
        "last": "Tyers", 
        "first": "Francis"
      }
    ], 
    "lang_name": "Kazakh"
  }, 
  {
    "lang_code": "ko", 
    "contributors": [], 
    "lang_name": "Korean"
  }, 
  {
    "lang_code": "la", 
    "contributors": [
      {
        "full": "Giuseppe G. A. Celano", 
        "last": "Celano", 
        "first": "Giuseppe G. A."
      }, 
      {
        "full": "Daniel Zeman", 
        "last": "Zeman", 
        "first": "Daniel"
      }
    ], 
    "lang_name": "Latin"
  }, 
  {
    "lang_code": "la_ittb", 
    "contributors": [
      {
        "full": "Marco Passarotti", 
        "last": "Passarotti", 
        "first": "Marco"
      }, 
      {
        "full": "Daniel Zeman", 
        "last": "Zeman", 
        "first": "Daniel"
      }, 
      {
        "full": "Berta Gonz\u00e1les Saavedra", 
        "last": "Gonz\u00e1les Saavedra", 
        "first": "Berta"
      }
    ], 
    "lang_name": "Latin-ITTB"
  }, 
  {
    "lang_code": "la_proiel", 
    "contributors": [
      {
        "full": "Dag Haug", 
        "last": "Haug", 
        "first": "Dag"
      }
    ], 
    "lang_name": "Latin-PROIEL"
  }, 
  {
    "lang_code": "lv", 
    "contributors": [
      {
        "full": "Lauma Pretkalni\u0146a", 
        "last": "Pretkalni\u0146a", 
        "first": "Lauma"
      }, 
      {
        "full": "Baiba Saul\u012bte", 
        "last": "Saul\u012bte", 
        "first": "Baiba"
      }, 
      {
        "full": "Laura Rituma", 
        "last": "Rituma", 
        "first": "Laura"
      }, 
      {
        "full": "Normunds Gr\u016bz\u012btis", 
        "last": "Gr\u016bz\u012btis", 
        "first": "Normunds"
      }
    ], 
    "lang_name": "Latvian"
  }, 
  {
    "lang_code": "no", 
    "contributors": [
      {
        "full": "Lilja \u00d8vrelid", 
        "last": "\u00d8vrelid", 
        "first": "Lilja"
      }
    ], 
    "lang_name": "Norwegian"
  }, 
  {
    "lang_code": "cu", 
    "contributors": [
      {
        "full": "Dag Haug", 
        "last": "Haug", 
        "first": "Dag"
      }
    ], 
    "lang_name": "Old_Church_Slavonic"
  }, 
  {
    "lang_code": "fa", 
    "contributors": [
      {
        "full": "Mojgan Seraji", 
        "last": "Seraji", 
        "first": "Mojgan"
      }, 
      {
        "full": "Filip Ginter", 
        "last": "Ginter", 
        "first": "Filip"
      }, 
      {
        "full": "Joakim Nivre", 
        "last": "Nivre", 
        "first": "Joakim"
      }
    ], 
    "lang_name": "Persian"
  }, 
  {
    "lang_code": "pl", 
    "contributors": [
      {
        "full": "Daniel Zeman", 
        "last": "Zeman", 
        "first": "Daniel"
      }, 
      {
        "full": "Jan Ma\u0161ek", 
        "last": "Ma\u0161ek", 
        "first": "Jan"
      }, 
      {
        "full": "Rudolf Rosa", 
        "last": "Rosa", 
        "first": "Rudolf"
      }
    ], 
    "lang_name": "Polish"
  }, 
  {
    "lang_code": "pt", 
    "contributors": [
      {
        "full": "Daniel Zeman", 
        "last": "Zeman", 
        "first": "Daniel"
      }, 
      {
        "full": "Martin Popel", 
        "last": "Popel", 
        "first": "Martin"
      }, 
      {
        "full": "David Mare\u010dek", 
        "last": "Mare\u010dek", 
        "first": "David"
      }, 
      {
        "full": "Natalia Silveira", 
        "last": "Silveira", 
        "first": "Natalia"
      }, 
      {
        "full": "Andr\u00e9 Martins", 
        "last": "Martins", 
        "first": "Andr\u00e9"
      }
    ], 
    "lang_name": "Portuguese"
  }, 
  {
    "lang_code": "pt_br", 
    "contributors": [
      {
        "full": "Ryan McDonald", 
        "last": "McDonald", 
        "first": "Ryan"
      }, 
      {
        "full": "Joakim Nivre", 
        "last": "Nivre", 
        "first": "Joakim"
      }, 
      {
        "full": "Daniel Zeman", 
        "last": "Zeman", 
        "first": "Daniel"
      }
    ], 
    "lang_name": "Portuguese-BR"
  }, 
  {
    "lang_code": "ro", 
    "contributors": [
      {
        "full": "Verginica Mititelu", 
        "last": "Mititelu", 
        "first": "Verginica"
      }, 
      {
        "full": "Elena Irimia", 
        "last": "Irimia", 
        "first": "Elena"
      }, 
      {
        "full": "Cenel-Augusto Perez", 
        "last": "Perez", 
        "first": "Cenel-Augusto"
      }, 
      {
        "full": "Radu Ion", 
        "last": "Ion", 
        "first": "Radu"
      }, 
      {
        "full": "Radu Simionescu", 
        "last": "Simionescu", 
        "first": "Radu"
      }, 
      {
        "full": "C\u0103t\u0103lina M\u0103r\u0103nduc", 
        "last": "M\u0103r\u0103nduc", 
        "first": "C\u0103t\u0103lina"
      }
    ], 
    "lang_name": "Romanian"
  }, 
  {
    "lang_code": "ru", 
    "contributors": [
      {
        "full": "Ryan McDonald", 
        "last": "McDonald", 
        "first": "Ryan"
      }, 
      {
        "full": "Vitaly Nikolaev", 
        "last": "Nikolaev", 
        "first": "Vitaly"
      }, 
      {
        "full": "Olga Lyashevskaya", 
        "last": "Lyashevskaya", 
        "first": "Olga"
      }
    ], 
    "lang_name": "Russian"
  }, 
  {
    "lang_code": "ru_syntagrus", 
    "contributors": [
      {
        "full": "Kira Droganova", 
        "last": "Droganova", 
        "first": "Kira"
      }, 
      {
        "full": "Olga Lyashevskaya", 
        "last": "Lyashevskaya", 
        "first": "Olga"
      }, 
      {
        "full": "Daniel Zeman", 
        "last": "Zeman", 
        "first": "Daniel"
      }, 
      {
        "full": "Lena Shakurova", 
        "last": "Shakurova", 
        "first": "Lena"
      }, 
      {
        "full": "Nina Mustafina", 
        "last": "Mustafina", 
        "first": "Nina"
      }
    ], 
    "lang_name": "Russian-SynTagRus"
  }, 
  {
    "lang_code": "sa", 
    "contributors": [
      {
        "full": "Puneet Dwivedi", 
        "last": "Dwivedi", 
        "first": "Puneet"
      }, 
      {
        "full": "Daniel Zeman", 
        "last": "Zeman", 
        "first": "Daniel"
      }
    ], 
    "lang_name": "Sanskrit"
  }, 
  {
    "lang_code": "sl", 
    "contributors": [
      {
        "full": "Kaja Dobrovoljc", 
        "last": "Dobrovoljc", 
        "first": "Kaja"
      }, 
      {
        "full": "Toma\u017e Erjavec", 
        "last": "Erjavec", 
        "first": "Toma\u017e"
      }, 
      {
        "full": "Simon Krek", 
        "last": "Krek", 
        "first": "Simon"
      }
    ], 
    "lang_name": "Slovenian"
  }, 
  {
    "lang_code": "sl_sst", 
    "contributors": [
      {
        "full": "Kaja Dobrovoljc", 
        "last": "Dobrovoljc", 
        "first": "Kaja"
      }, 
      {
        "full": "Joakim Nivre", 
        "last": "Nivre", 
        "first": "Joakim"
      }
    ], 
    "lang_name": "Slovenian-SST"
  }, 
  {
    "lang_code": "es", 
    "contributors": [
      {
        "full": "Miguel Ballesteros", 
        "last": "Ballesteros", 
        "first": "Miguel"
      }, 
      {
        "full": "H\u00e9ctor Mart\u00ednez Alonso", 
        "last": "Mart\u00ednez Alonso", 
        "first": "H\u00e9ctor"
      }, 
      {
        "full": "Ryan McDonald", 
        "last": "McDonald", 
        "first": "Ryan"
      }, 
      {
        "full": "Elena Pascual", 
        "last": "Pascual", 
        "first": "Elena"
      }, 
      {
        "full": "Natalia Silveira", 
        "last": "Silveira", 
        "first": "Natalia"
      }, 
      {
        "full": "Daniel Zeman", 
        "last": "Zeman", 
        "first": "Daniel"
      }, 
      {
        "full": "Joakim Nivre", 
        "last": "Nivre", 
        "first": "Joakim"
      }
    ], 
    "lang_name": "Spanish"
  }, 
  {
    "lang_code": "es_ancora", 
    "contributors": [
      {
        "full": "H\u00e9ctor Mart\u00ednez Alonso", 
        "last": "Mart\u00ednez Alonso", 
        "first": "H\u00e9ctor"
      }, 
      {
        "full": "Daniel Zeman", 
        "last": "Zeman", 
        "first": "Daniel"
      }
    ], 
    "lang_name": "Spanish-AnCora"
  }, 
  {
    "lang_code": "sv", 
    "contributors": [
      {
        "full": "Joakim Nivre", 
        "last": "Nivre", 
        "first": "Joakim"
      }, 
      {
        "full": "Aaron Smith", 
        "last": "Smith", 
        "first": "Aaron"
      }
    ], 
    "lang_name": "Swedish"
  }, 
  {
    "lang_code": "sv_lines", 
    "contributors": [
      {
        "full": "Lars Ahrenberg", 
        "last": "Ahrenberg", 
        "first": "Lars"
      }
    ], 
    "lang_name": "Swedish-LinES"
  }, 
  {
    "lang_code": "ta", 
    "contributors": [
      {
        "full": "Loganathan Ramasamy", 
        "last": "Ramasamy", 
        "first": "Loganathan"
      }, 
      {
        "full": "Daniel Zeman", 
        "last": "Zeman", 
        "first": "Daniel"
      }
    ], 
    "lang_name": "Tamil"
  }, 
  {
    "lang_code": "tr", 
    "contributors": [
      {
        "full": "\u00c7a\u011fr\u0131 \u00c7\u00f6ltekin", 
        "last": "\u00c7\u00f6ltekin", 
        "first": "\u00c7a\u011fr\u0131"
      }, 
      {
        "full": "G\u00fcl\u015fen Cebiro\u011flu Eryi\u011fit", 
        "last": "Cebiro\u011flu Eryi\u011fit", 
        "first": "G\u00fcl\u015fen"
      }, 
      {
        "full": "Memduh G\u00f6k\u0131rmak", 
        "last": "G\u00f6k\u0131rmak", 
        "first": "Memduh"
      }, 
      {
        "full": "H\u00fcner Ka\u015f\u0131kara", 
        "last": "Ka\u015f\u0131kara", 
        "first": "H\u00fcner"
      }, 
      {
        "full": "Umut Sulubacak", 
        "last": "Sulubacak", 
        "first": "Umut"
      }, 
      {
        "full": "Francis Tyers", 
        "last": "Tyers", 
        "first": "Francis"
      }
    ], 
    "lang_name": "Turkish"
  }, 
  {
    "lang_code": "uk", 
    "contributors": [], 
    "lang_name": "Ukrainian"
  }, 
  {
    "lang_code": "ug", 
    "contributors": [
      {
        "full": "Marhaba Eli", 
        "last": "Eli", 
        "first": "Marhaba"
      }
    ], 
    "lang_name": "Uyghur"
  }, 
  {
    "lang_code": "vi", 
    "contributors": [], 
    "lang_name": "Vietnamese"
  }
]