{
"Finnish":"FI",
"Swedish":"SE",
"Finnish-FTB":"FI",
"Czech":"CZ",
"Amharic":"ET",
"Ancient_Greek":"GR",
"Ancient_Greek-PROIEL":"GR",
"Arabic":"SA-AL",
"Basque":"ES-PV",
"Bulgarian":"BG",
"Catalan":"ES-CT",
"Chinese":"CN",
"Croatian":"HR",
"Danish":"DK",
"Dutch":"NL",
"English":"GB",
"Estonian":"EE",
"French":"FR",
"German":"DE",
"Gothic":"BYZ",
"Greek":"GR",
"Hebrew":"IL",
"Hindi":"IN",
"Hungarian":"HU",
"Indonesian":"ID",
"Irish":"IE",
"Italian":"IT",
"Latin":"VA",
"Latin-ITT":"VA",
"Latin-PROIEL":"VA",
"Japanese":"JP",
"Japanese-KTC":"JP",
"Korean":"KR",
"Old_Church_Slavonic":"MORAVA",
"Persian":"IR",
"Polish":"PL",
"Portuguese":"PT",
"Romanian":"RO",
"Slovenian":"SI",
"Spanish":"ES",
"Tamil":"IN",
"Kazakh":"KZ",
"Turkish":"TR",
"Polish":"PL",
"Norwegian":"NO"
}
